{"key":"plugin_content_manager_configuration_content_types::api::connection-list.connection-list","value":{"uid":"api::connection-list.connection-list","settings":{"bulkable":true,"filterable":true,"searchable":true,"pageSize":10,"mainField":"dramaMakerName","defaultSortBy":"dramaMakerName","defaultSortOrder":"ASC"},"metadatas":{"id":{"edit":{},"list":{"label":"تسلسل","searchable":true,"sortable":true}},"dramaMakerName":{"edit":{"label":"اسم صانع العمل","description":"","placeholder":"","visible":true,"editable":true},"list":{"label":"اسم صانع العمل","searchable":true,"sortable":true}},"talentName":{"edit":{"label":"اسم عضو النقابه","description":"","placeholder":"","visible":true,"editable":true},"list":{"label":"اسم عضو النقابه","searchable":true,"sortable":true}},"talentInfo":{"edit":{"label":"عضو النقابة","description":"","placeholder":"","visible":true,"editable":true,"mainField":"resetPasswordToken"},"list":{"label":"عضو النقابة","searchable":true,"sortable":true}},"connectionDate":{"edit":{"label":"تاريخ الاتصال","description":"","placeholder":"","visible":true,"editable":true},"list":{"label":"تاريخ الاتصال","searchable":true,"sortable":true}},"connectionTime":{"edit":{"label":"وقت الاتصال","description":"","placeholder":"","visible":true,"editable":true},"list":{"label":"وقت الاتصال","searchable":true,"sortable":true}},"createdAt":{"edit":{"label":"createdAt","description":"","placeholder":"","visible":false,"editable":true},"list":{"label":"تاريخ الانشاء","searchable":true,"sortable":true}},"updatedAt":{"edit":{"label":"updatedAt","description":"","placeholder":"","visible":false,"editable":true},"list":{"label":"تاريخ التعديل","searchable":true,"sortable":true}}},"layouts":{"edit":[[{"name":"dramaMakerName","size":6},{"name":"talentName","size":6}],[{"name":"talentInfo","size":6}],[{"name":"connectionDate","size":4},{"name":"connectionTime","size":4}]],"list":["id","dramaMakerName","talentName","talentInfo"]}},"type":"object","environment":null,"tag":null}